frappe_local_backup/__init__.py
frappe_local_backup/api.py
frappe_local_backup/backup_service.py
frappe_local_backup/cli.py
frappe_local_backup/config.py
frappe_local_backup/credentials.py
frappe_local_backup/database.py
frappe_local_backup/frappe_client.py
frappe_local_backup-1.0.6.dist-info/licenses/LICENSE
scripts/bump_version.py
tests/__init__.py
tests/conftest.py
tests/test_backup_service.py
tests/test_cli.py
tests/test_config.py
tests/test_database.py
tests/test_frappe_client.py
frappe_local_backup-1.0.6.dist-info/METADATA
frappe_local_backup-1.0.6.dist-info/WHEEL
frappe_local_backup-1.0.6.dist-info/entry_points.txt
frappe_local_backup-1.0.6.dist-info/top_level.txt
frappe_local_backup-1.0.6.dist-info/RECORD
