Metadata-Version: 2.4
Name: frappe-local-backup
Version: 1.0.6
Summary: Backup service for Frappe Cloud sites - Download and manage backups locally
Author-email: Hawre <hawre.salih@outlook.com>
License: MIT
Project-URL: Homepage, https://github.com/hawre1987/frappe-local-backup
Project-URL: Documentation, https://github.com/hawre1987/frappe-local-backup#readme
Project-URL: Repository, https://github.com/hawre1987/frappe-local-backup.git
Project-URL: Issues, https://github.com/hawre1987/frappe-local-backup/issues
Keywords: frappe,erpnext,backup,frappe-cloud,automation
Classifier: Development Status :: 4 - Beta
Classifier: Environment :: Console
Classifier: Intended Audience :: System Administrators
Classifier: Intended Audience :: Developers
Classifier: License :: OSI Approved :: MIT License
Classifier: Operating System :: POSIX :: Linux
Classifier: Programming Language :: Python :: 3
Classifier: Programming Language :: Python :: 3.10
Classifier: Programming Language :: Python :: 3.11
Classifier: Programming Language :: Python :: 3.12
Classifier: Topic :: System :: Archiving :: Backup
Classifier: Topic :: System :: Systems Administration
Requires-Python: >=3.10
License-File: LICENSE
Requires-Dist: requests>=2.31.0
Requires-Dist: fastapi>=0.109.0
Requires-Dist: uvicorn[standard]>=0.27.0
Requires-Dist: python-dotenv>=1.0.0
Requires-Dist: click>=8.1.0
Requires-Dist: rich>=13.7.0
Requires-Dist: pydantic>=2.5.0
Requires-Dist: pydantic-settings>=2.1.0
Requires-Dist: apscheduler>=3.10.0
Requires-Dist: keyring>=24.0.0
Requires-Dist: keyrings.alt>=5.0.0
Requires-Dist: pycryptodome>=3.20.0
Provides-Extra: dev
Requires-Dist: pytest>=7.0.0; extra == "dev"
Requires-Dist: pytest-cov>=4.0.0; extra == "dev"
Requires-Dist: black>=23.0.0; extra == "dev"
Requires-Dist: ruff>=0.1.0; extra == "dev"
Provides-Extra: secure-storage
Requires-Dist: pycryptodome>=3.20.0; extra == "secure-storage"
Provides-Extra: gnome
Requires-Dist: secretstorage>=3.3.0; extra == "gnome"
Dynamic: license-file
